setup.py
prioritymatrix/__init__.py
prioritymatrix/icon.py
prioritymatrix/item.py
prioritymatrix/pm.py
prioritymatrix/project.py
prioritymatrix/user.py
prioritymatrix.egg-info/PKG-INFO
prioritymatrix.egg-info/SOURCES.txt
prioritymatrix.egg-info/dependency_links.txt
prioritymatrix.egg-info/not-zip-safe
prioritymatrix.egg-info/top_level.txt