Metadata-Version: 1.1
Name: prioritymatrix
Version: 0.1
Summary: Priority Matrix API
Home-page: https://github.com/samuc/prioritymatrix-python
Author: Samuel Carmona
Author-email: samuel@appfluence.com
License: MIT
Download-URL: https://github.com/samuc/prioritymatrix-python/tarball/0.1
Platform: UNKNOWN
